alphaj_naver_stock_info_crawler/ExcelHandler.py
alphaj_naver_stock_info_crawler/PriceCralwer.py
alphaj_naver_stock_info_crawler/SheetHandler.py
alphaj_naver_stock_info_crawler/Util.py
alphaj_naver_stock_info_crawler/Validator.py
alphaj_naver_stock_info_crawler/Valuation.py
alphaj_naver_stock_info_crawler/__init__.py
alphaj_naver_stock_info_crawler/constant.py
alphaj_naver_stock_cralwer-0.1.11.dist-info/METADATA
alphaj_naver_stock_cralwer-0.1.11.dist-info/WHEEL
alphaj_naver_stock_cralwer-0.1.11.dist-info/top_level.txt
alphaj_naver_stock_cralwer-0.1.11.dist-info/RECORD
