Metadata-Version: 2.1
Name: alphaj-naver-stock-cralwer
Version: 0.1.11
Summary: A Naver Stock Cralwer
Home-page: UNKNOWN
Author: Alpha J
Author-email: jaeminyx@gmail.com
License: UNKNOWN
Platform: UNKNOWN
Classifier: Programming Language :: Python :: 3
Classifier: License :: OSI Approved :: MIT License
Classifier: Operating System :: OS Independent
Requires-Dist: setuptools (==39.0.1)
Requires-Dist: openpyxl (==2.5.4)
Requires-Dist: Unidecode (==1.0.22)
Requires-Dist: pytest (==3.0.7)
Requires-Dist: requests (==2.18.4)
Requires-Dist: pandas (==0.23.3)
